unreal_llm_sandbox/__init__.py
unreal_llm_sandbox/_modidx.py
unreal_llm_sandbox/app_config.py
unreal_llm_sandbox/cells.py
unreal_llm_sandbox/llm.py
unreal_llm_sandbox/llm_tools.py
unreal_llm_sandbox/main.py
unreal_llm_sandbox/notebook_io.py
unreal_llm_sandbox/streaming.py
unreal_llm_sandbox-0.0.3.dist-info/licenses/LICENSE
unreal_llm_sandbox-0.0.3.dist-info/METADATA
unreal_llm_sandbox-0.0.3.dist-info/WHEEL
unreal_llm_sandbox-0.0.3.dist-info/entry_points.txt
unreal_llm_sandbox-0.0.3.dist-info/top_level.txt
unreal_llm_sandbox-0.0.3.dist-info/RECORD
