Metadata-Version: 2.4
Name: unreal-llm-sandbox
Version: 0.0.3
Summary: LLM Sandbox For Unreal Engine
Home-page: https://github.com/NeuralVFX/unreal-llm-sandbox
Author: NeuralVFX
Author-email: neuralvfx@gmail.com
License: MIT License
Keywords: nbdev jupyter notebook python
Classifier: Development Status :: 4 - Beta
Classifier: Intended Audience :: Developers
Classifier: Natural Language :: English
Classifier: Programming Language :: Python :: 3.9
Classifier: Programming Language :: Python :: 3.10
Classifier: Programming Language :: Python :: 3.11
Classifier: Programming Language :: Python :: 3.12
Classifier: License :: OSI Approved :: MIT License
Requires-Python: >=3.9
License-File: LICENSE
Requires-Dist: fastcore
Requires-Dist: requests
Requires-Dist: litellm
Requires-Dist: lisette
Requires-Dist: python-fasthtml
Requires-Dist: mistune
Requires-Dist: pillow
Requires-Dist: starlette
Requires-Dist: ddgs
Provides-Extra: dev
Dynamic: author
Dynamic: author-email
Dynamic: classifier
Dynamic: description
Dynamic: description-content-type
Dynamic: home-page
Dynamic: keywords
Dynamic: license
Dynamic: license-file
Dynamic: provides-extra
Dynamic: requires-dist
Dynamic: requires-python
Dynamic: summary
